global_land_mask_oc/__init__.py
global_land_mask_oc/global-land-mask-oc.npz
global_land_mask_oc/globe.py
global_land_mask_oc-1.0.0.dist-info/licenses/LICENSE
global_land_mask_oc-1.0.0.dist-info/METADATA
global_land_mask_oc-1.0.0.dist-info/WHEEL
global_land_mask_oc-1.0.0.dist-info/top_level.txt
global_land_mask_oc-1.0.0.dist-info/RECORD
