Metadata-Version: 2.4
Name: global-land-mask-oc
Version: 1.0.0
Summary: Global land mask for satellite ocean color remote sensing
Home-page: https://github.com/fengqiaogh/global-land-mask-oc
Author: feng qiao
Author-email: Feng Qiao <qiaofengwy@163.com>
Requires-Python: >=3.13
License-File: LICENSE
Requires-Dist: numpy>=2.3.1
Dynamic: author
Dynamic: home-page
Dynamic: license-file
